contouring/__init__.py
contouring/contouring.py
petri_contouring-0.1.3.dist-info/METADATA
petri_contouring-0.1.3.dist-info/WHEEL
petri_contouring-0.1.3.dist-info/top_level.txt
petri_contouring-0.1.3.dist-info/RECORD
