Metadata-Version: 2.1
Name: petri-contouring
Version: 0.1.3
Summary: Petri Elliptic Contouring Package
Home-page: https://github.com/Elessar11777
Author: Elessar11777
Author-email: Elessar11777@gmail.com
Requires-Dist: numpy >=1.21.0
Requires-Dist: opencv-python >=4.5.3
